castrel_proxy/__init__.py
castrel_proxy/cli/__init__.py
castrel_proxy/cli/commands.py
castrel_proxy/core/__init__.py
castrel_proxy/core/client_id.py
castrel_proxy/core/config.py
castrel_proxy/core/daemon.py
castrel_proxy/core/executor.py
castrel_proxy/data/__init__.py
castrel_proxy/data/default_whitelist.txt
castrel_proxy/mcp/__init__.py
castrel_proxy/mcp/manager.py
castrel_proxy/network/__init__.py
castrel_proxy/network/api_client.py
castrel_proxy/network/websocket_client.py
castrel_proxy/operations/__init__.py
castrel_proxy/operations/document.py
castrel_proxy/security/__init__.py
castrel_proxy/security/whitelist.py
castrel_proxy-0.1.3.dist-info/METADATA
castrel_proxy-0.1.3.dist-info/WHEEL
castrel_proxy-0.1.3.dist-info/entry_points.txt
castrel_proxy-0.1.3.dist-info/licenses/LICENSE
castrel_proxy-0.1.3.dist-info/RECORD
