Metadata-Version: 2.4
Name: castrel-proxy
Version: 0.1.3
Summary: A lightweight remote command execution bridge client with MCP integration
Project-URL: Homepage, https://github.com/castrel-ai/castrel-proxy
Project-URL: Documentation, https://github.com/castrel-ai/castrel-proxy#readme
Project-URL: Repository, https://github.com/castrel-ai/castrel-proxy
Project-URL: Issues, https://github.com/castrel-ai/castrel-proxy/issues
Project-URL: Changelog, https://github.com/castrel-ai/castrel-proxy/blob/main/CHANGELOG.md
Author: Castrel Team
License: MIT License
License-File: LICENSE
Keywords: bridge,mcp,proxy,remote-execution,websocket
Classifier: Development Status :: 3 - Alpha
Classifier: Intended Audience :: Developers
Classifier: License :: OSI Approved :: MIT License
Classifier: Operating System :: OS Independent
Classifier: Programming Language :: Python :: 3
Classifier: Programming Language :: Python :: 3.10
Classifier: Programming Language :: Python :: 3.11
Classifier: Programming Language :: Python :: 3.12
Classifier: Programming Language :: Python :: 3.13
Classifier: Topic :: Software Development :: Libraries :: Python Modules
Classifier: Topic :: System :: Networking
Requires-Python: >=3.10
Requires-Dist: aiohttp>=3.9.0
Requires-Dist: langchain-mcp-adapters>=0.2.1
Requires-Dist: mcp>=1.0.0
Requires-Dist: pyyaml>=6.0.1
Requires-Dist: typer>=0.20.1
Provides-Extra: dev
Requires-Dist: black>=23.0.0; extra == 'dev'
Requires-Dist: flake8>=6.0.0; extra == 'dev'
Requires-Dist: isort>=5.12.0; extra == 'dev'
Requires-Dist: mypy>=1.0.0; extra == 'dev'
Requires-Dist: pytest-asyncio>=0.21.0; extra == 'dev'
Requires-Dist: pytest-cov>=4.0.0; extra == 'dev'
Requires-Dist: pytest>=7.0.0; extra == 'dev'
